{
    "id": 1280,
    "name": "Margma",
    "creators": [
        "Dracorex"
    ],
    "verifier": "Dracorex",
    "verification": "#",
    "records": [
        {
            "user": "N5LX",
            "link": "#",
            "percent": 100,
            "mobile": false
        },
        {
            "user": "Razlboy",
            "link": "#",
            "percent": 100,
            "mobile": false
        },
        {
            "user": "Grayson",
            "link": "#",
            "percent": 100,
            "mobile": true
        },
        {
            "user": "nightsIris",
            "link": "#",
            "percent": 100,
            "mobile": false
        },
        {
            "user": "Herobrain",
            "link": "#",
            "percent": 100,
            "mobile": false
        },
        {
            "user": "MacacoChucrut",
            "link": "#",
            "percent": 100,
            "mobile": false
        },
        {
            "user": "Quantium",
            "link": "#",
            "percent": 100,
            "mobile": true
        }
    ],
    "tags": [
        "Overall",
        "Slow-Paced",
        "Medium"
    ]
}