{
    "id": 3745,
    "name": "void of reason",
    "author": "nightsIris",
  "creators": ["nightsIris"],
    "verifier": "nightsIris",
    "verification": "#",
    "percentToQualify": "100",
    "difficulty": "Medium Demon",
    "records": [
         {
            "user": "Herobrain",
            "link": "#",
            "percent": 100,
            "mobile": false
        },
        {
            "user": "Quantium",
            "link": "#",
            "percent": 100,
            "mobile": true
        }
    ],
  "tags": ["Cube", "Wave", "Timings", "Medium", "Memory"]
}
